{
  "type": "pfm:furniture",
  "group": "kitchen",
  "ingredients": [
    {
      "item": "quark:polished_limestone"
    },
    {
      "item": "quark:polished_limestone"
    },
    {
      "item": "quark:polished_limestone"
    },
    {
      "item": "quark:polished_limestone"
    },
    {
      "item": "quark:polished_limestone"
    },
    {
      "item": "quark:polished_limestone"
    },
    {
      "item": "quark:limestone"
    },
    {
      "item": "quark:limestone"
    },
    {
      "item": "quark:limestone"
    }
  ],
  "result": {
    "item": "pfm:limestone_quark_kitchen_counter",
    "count": 6
  }
}