{
  "parent": "minecraft:recipes/root",
  "rewards": {
    "recipes": [
      "pfm:cut_diorite_create_table_modern_dinner"
    ]
  },
  "criteria": {
    "cut_diorite_create_table_modern_dinner": {
      "trigger": "minecraft:inventory_changed",
      "conditions": {
        "items": [
          {
            "items": [
              "create:polished_cut_diorite"
            ]
          }
        ]
      }
    },
    "has_the_recipe": {
      "trigger": "minecraft:recipe_unlocked",
      "conditions": {
        "recipe": "pfm:cut_diorite_create_table_modern_dinner"
      }
    }
  },
  "requirements": [
    [
      "cut_diorite_create_table_modern_dinner",
      "has_the_recipe"
    ]
  ]
}